picoQuantum/Demo.py
picoQuantum/__init__.py
picoQuantum/heat.py
picoQuantum/heat_old.py
picoQuantum/io.py
picoQuantum/sympytest.py
picoQuantum-0.1.3.dist-info/METADATA
picoQuantum-0.1.3.dist-info/WHEEL
picoQuantum-0.1.3.dist-info/top_level.txt
picoQuantum-0.1.3.dist-info/RECORD
