Metadata-Version: 2.1
Name: picoQuantum
Version: 0.1.3
Summary: Package for solving quantum heat problems in the linear regime
Author: Andrew Guthrie
Author-email: <andrew.guthrie@aalto.fi>
Keywords: python,first package
Classifier: Development Status :: 3 - Alpha
Classifier: Intended Audience :: Education
Classifier: Programming Language :: Python :: 2
Classifier: Programming Language :: Python :: 3
Classifier: Operating System :: MacOS :: MacOS X
Classifier: Operating System :: Microsoft :: Windows
